[
  {
    "id": "214704842",
    "from": "2026-02-09 11:45:51",
    "title": "Vila u moře k rekonstrukci🇮🇹",
    "price_formatted": "2 200 000 Kč",
    "currency": "CZK",
    "image_thumbnail": "https://www.bazos.cz/img/1m/842/214704842.jpg?t=1770559745",
    "locality": "Frýdek - Místek",
    "topped": "true",
    "image_thumbnail_width": "350",
    "image_thumbnail_height": "233",
    "favourite": "false",
    "url": "https://reality.bazos.cz/inzerat/214704842/vila-u-more-k-rekonstrukci.php",
    "views": "2431"
  },
  {
    "id": "214693429",
    "from": "2026-02-09 11:45:51",
    "title": ": Pronájem pozemku pro samoobslužnou myčku. Povolení ano",
    "price_formatted": "19 Kč",
    "currency": "CZK",
    "image_thumbnail": "https://www.bazos.cz/img/1m/429/214693429.jpg?t=1770547933",
    "locality": "Teplice",
    "topped": "true",
    "image_thumbnail_width": "350",
    "image_thumbnail_height": "256",
    "favourite": "false",
    "url": "https://reality.bazos.cz/inzerat/214693429/pronajem-pozemku-pro-samoobsluznou-mycku-povoleni-ano.php",
    "views": "342"
  },
  {
    "id": "214144926",
    "from": "2026-02-09 11:45:51",
    "title": "Stavebni pozemek u moře🇮🇹",
    "price_formatted": "1 100 000 Kč",
    "currency": "CZK",
    "image_thumbnail": "https://www.bazos.cz/img/1m/926/214144926.jpg?t=1770376042",
    "locality": "Frýdek - Místek",
    "topped": "true",
    "image_thumbnail_width": "350",
    "image_thumbnail_height": "263",
    "favourite": "false",
    "url": "https://reality.bazos.cz/inzerat/214144926/stavebni-pozemek-u-more.php",
    "views": "3510"
  },
  {
    "id": "214464437",
    "from": "2026-02-09 11:45:51",
    "title": "Moderní apartmány 2KK v Sea Paradise Apartments",
    "price_formatted": "2 457 000 Kč",
    "currency": "CZK",
    "image_thumbnail": "https://www.bazos.cz/img/1m/437/214464437.jpg?t=1770325226",
    "locality": "Zahraničí",
    "topped": "true",
    "image_thumbnail_width": "347",
    "image_thumbnail_height": "350",
    "favourite": "false",
    "url": "https://reality.bazos.cz/inzerat/214464437/moderni-apartman-s-dispozici-2kk-v-sea-paradise-apartments.php",
    "views": "2237"
  },
  {
    "id": "214410493",
    "from": "2026-02-09 11:45:51",
    "title": "EXKLUSIVNÍ APARTMÁN VE VELKÝCH KARLOVICÍCH",
    "price_formatted": "7 390 000 Kč",
    "currency": "CZK",
    "image_thumbnail": "https://www.bazos.cz/img/1m/493/214410493.jpg?t=1770127933",
    "locality": "Vsetín",
    "topped": "true",
    "image_thumbnail_width": "350",
    "image_thumbnail_height": "233",
    "favourite": "false",
    "url": "https://reality.bazos.cz/inzerat/214410493/exklusivni-apartman-ve-velkych-karlovicich.php",
    "views": "1940"
  }
]